MANIFEST.in
setup.cfg
setup.py
rpctools/__init__.py
rpctools/six.py
rpctools.egg-info/PKG-INFO
rpctools.egg-info/SOURCES.txt
rpctools.egg-info/dependency_links.txt
rpctools.egg-info/top_level.txt
rpctools.egg-info/zip-safe
rpctools/jsonrpc/__init__.py
rpctools/jsonrpc/client.py
rpctools/jsonrpc/exc.py
rpctools/jsonrpc/pool.py
rpctools/jsonrpc/ssl_wrapper.py
rpctools/jsonrpc/transport.py