Metadata-Version: 1.1
Name: rpctools
Version: 0.3.1
Summary: 
